Metadata-Version: 2.1
Name: plover-clipboard
Version: 1.0
Summary: Plover plugin for accessing the system clipboard
Home-page: https://github.com/sammdot/plover-clipboard
License: UNKNOWN
Keywords: plover plover_plugin
Platform: UNKNOWN
Classifier: Programming Language :: Python :: 3.6
Classifier: Programming Language :: Python :: 3.7
Classifier: Programming Language :: Python :: 3.8
Classifier: Programming Language :: Python :: 3.9
